cryovit_napari/__init__.py
cryovit_napari/_cryovit.py
cryovit_napari/_dataset.py
cryovit_napari/_inference.py
cryovit_napari/_reader.py
cryovit_napari/_training.py
cryovit_napari/_version.py
cryovit_napari/napari.yaml
cryovit_napari/_tests/__init__.py
cryovit_napari/_tests/test_dataset.py
cryovit_napari/_tests/test_reader.py
cryovit_napari-0.1.0.dist-info/licenses/LICENSE
cryovit_napari-0.1.0.dist-info/METADATA
cryovit_napari-0.1.0.dist-info/WHEEL
cryovit_napari-0.1.0.dist-info/entry_points.txt
cryovit_napari-0.1.0.dist-info/top_level.txt
cryovit_napari-0.1.0.dist-info/RECORD
