Metadata-Version: 2.4
Name: cryovit-napari
Version: 0.1.0
Summary: A simple plugin to train and run CryoViT models in napari
Author-email: Vivian Li <vdl21@cantab.ac.uk>
License: 
Classifier: Development Status :: 2 - Pre-Alpha
Classifier: Framework :: napari
Classifier: Intended Audience :: Developers
Classifier: License :: OSI Approved :: BSD License
Classifier: Operating System :: OS Independent
Classifier: Programming Language :: Python
Classifier: Programming Language :: Python :: 3
Classifier: Programming Language :: Python :: 3 :: Only
Classifier: Programming Language :: Python :: 3.10
Classifier: Programming Language :: Python :: 3.11
Classifier: Programming Language :: Python :: 3.12
Classifier: Programming Language :: Python :: 3.13
Classifier: Topic :: Scientific/Engineering :: Image Processing
Requires-Python: >=3.10
License-File: LICENSE
Requires-Dist: numpy
Requires-Dist: magicgui
Requires-Dist: qtpy
Requires-Dist: psygnal
Requires-Dist: napari
Requires-Dist: cryovit
Requires-Dist: loguru
Provides-Extra: all
Requires-Dist: napari[all]; extra == "all"
Dynamic: license-file
